{
	"class" : {
		"algertemList" : "lm 5/25/2021 21:19",
		"allWindowActions" : "lm 7/5/2021 22:40",
		"icon" : "NL 6/4/2021 14:20",
		"visibleWindows" : "lm 5/25/2021 21:14" },
	"instance" : {
		"bringWindowToFront" : "b 5/27/2021 12:51",
		"closeAllWindowsButThis" : "lm 5/25/2021 21:01",
		"closeAllWindowsLikeThis" : "lm 5/25/2021 21:03",
		"closeWindow" : "lm 5/25/2021 20:56",
		"collapseWindow" : "lm 5/25/2021 20:47",
		"contractWindow" : "lm 5/25/2021 20:53",
		"createActionBringToFront" : "lm 5/26/2021 19:48",
		"createActionClose" : "lm 5/25/2021 21:34",
		"createActionCloseAllButThis" : "lm 5/25/2021 21:33",
		"createActionCloseAllLikeThis" : "lm 5/25/2021 21:33",
		"createActionCollapse" : "lm 5/25/2021 22:08",
		"createActionContract" : "lm 5/25/2021 21:35",
		"createActionExpand" : "lm 5/25/2021 21:35",
		"createListOfAlgeractions" : "lm 5/25/2021 21:11",
		"expandWindow" : "lm 5/25/2021 20:52",
		"hasChildren" : "lm 5/25/2021 21:37",
		"name" : "lm 5/25/2021 21:16",
		"rankBonus" : "lm 5/25/2021 21:35",
		"typeName" : "lm 5/25/2021 20:36" } }
