{
	"class" : {
		"backgroundColor" : "J.J. 7/28/2015 20:12",
		"cursorColor" : "beb 5/29/2020 19:07",
		"defaultFont" : "DS 5/11/2017 10:57" },
	"instance" : {
		"clear" : "J.J. 7/27/2015 20:02",
		"controller" : "J.J. 7/28/2015 20:13",
		"controller:" : "J.J. 7/28/2015 20:13",
		"createParagraph" : "rk 6/17/2020 13:52",
		"currentContent" : "J.J. 7/27/2015 21:43",
		"cursorWrapped:" : "Jro 6/16/2020 18:18",
		"handlesKeyboard:" : "rk 8/3/2020 16:45",
		"highlightAttribute" : "YD 5/13/2022 14:13",
		"highlightAttribute:" : "YD 5/13/2022 14:13",
		"highlightInterval:" : "YD 5/15/2022 20:40",
		"highlightKeyword" : "YD 5/13/2022 14:51",
		"initialize" : "YD 5/13/2022 15:04",
		"initializeKeywords" : "YD 5/13/2022 15:03",
		"isEmpty" : "td 6/29/2016 08:11",
		"keyStroke:" : "YD 5/13/2022 14:53",
		"keyboardFocusColor" : "NM 6/1/2021 19:06",
		"keywordIntervalFor:" : "YD 5/15/2022 20:31",
		"keywords" : "YD 5/13/2022 15:00",
		"keywords:" : "YD 5/13/2022 15:00",
		"moveCursorToEnd" : "rk 6/17/2020 14:00",
		"normalKeyStroke:" : "YD 5/13/2022 14:54",
		"size" : "beb 5/23/2020 16:04",
		"wouldAcceptKeyboardFocusUponTab" : "jRo 8/5/2020 16:20" } }
